ArcGISColor/__init__.py
ArcGISColor/color_cim.py
ArcGISColor/graphs.py
arcgiscolor-1.0.1.dist-info/WHEEL
arcgiscolor-1.0.1.dist-info/METADATA
arcgiscolor-1.0.1.dist-info/RECORD
