Metadata-Version: 2.1
Name: arcgiscolor
Version: 1.0.1
Summary: Toolset to apply coloring to a layer in an ArcGIS Pro map, using the greedy color method
License: MIT
Author: Cody Scott
Author-email: jcodyscott@gmail.com
Requires-Python: >=3.6,<4.0
Classifier: License :: OSI Approved :: MIT License
Classifier: Programming Language :: Python :: 3
Classifier: Programming Language :: Python :: 3.10
Classifier: Programming Language :: Python :: 3.6
Classifier: Programming Language :: Python :: 3.7
Classifier: Programming Language :: Python :: 3.8
Classifier: Programming Language :: Python :: 3.9
Requires-Dist: networkx (>=2.6.3,<3.0.0)
